maxminconquer/__init__.py
maxminconquer/find_max.py
maxminconquer/find_min.py
maxminconquer-0.1.4.dist-info/METADATA
maxminconquer-0.1.4.dist-info/WHEEL
maxminconquer-0.1.4.dist-info/top_level.txt
maxminconquer-0.1.4.dist-info/RECORD
